README.rst
named_constants.py
setup.py
named_constants.egg-info/PKG-INFO
named_constants.egg-info/SOURCES.txt
named_constants.egg-info/dependency_links.txt
named_constants.egg-info/top_level.txt