Metadata-Version: 1.1
Name: named-constants
Version: 1.0
Summary: This module offers an easy way to define named constants in Python, supporting some simple enum-like use case, as well as arbitrary value types like strings or floats.
Home-page: https://github.com/hmeine/named_constants
Author: Hans Meine
Author-email: hans_meine@gmx.net
License: Apache 2.0
Platform: UNKNOWN
Classifier: Development Status :: 5 - Production/Stable
Classifier: License :: OSI Approved :: Apache Software License
Classifier: Operating System :: OS Independent
Classifier: Programming Language :: Python :: 2
